swagger_stub/__init__.py
swagger_stub/swagger_stub.py
swagger_stub-0.2.1.dist-info/top_level.txt
swagger_stub-0.2.1.dist-info/METADATA
swagger_stub-0.2.1.dist-info/DESCRIPTION.rst
swagger_stub-0.2.1.dist-info/metadata.json
swagger_stub-0.2.1.dist-info/WHEEL
swagger_stub-0.2.1.dist-info/RECORD
