Metadata-Version: 2.0
Name: swagger-stub
Version: 0.2.1
Summary: Generate a stub from a swagger file
Home-page: https://github.com/Trax-air/swagger-stub
Author: Cyprien Guillemot
Author-email: cyprien.guillemot@gmail.com
License: MIT
Keywords: swagger,stub,API,REST,swagger-stub
Platform: UNKNOWN
Classifier: Development Status :: 5 - Production/Stable
Classifier: Intended Audience :: Developers
Classifier: License :: OSI Approved :: MIT License
Classifier: Natural Language :: English
Classifier: Programming Language :: Python :: 2
Classifier: Programming Language :: Python :: 2.7
Classifier: Programming Language :: Python :: 3
Classifier: Programming Language :: Python :: 3.3
Classifier: Programming Language :: Python :: 3.4
Requires-Dist: httpretty (>=0.8.14)
Requires-Dist: pytest (>=2.7.0)
Requires-Dist: swagger-parser (>=0.1)
